{"Resources":[{"Name":"SampleImage","Schema":"i","IsSampleData":true,"IsWritable":false,"Type":"ResourceInfo","FileName":"/ctrllib/image/images/SampleImage.svg","Path":"/ctrllib/image/images/SampleImage.svg","Content":"Image","ResourceKind":"Uri","RootPath":"ms-appx:///ctrllib/image/images/SampleImage.svg"},{"Name":"powertools","Schema":"i","IsSampleData":false,"IsWritable":false,"Type":"ResourceInfo","FileName":"0001.png","Path":"Assets\\Images\\0001.png","Content":"Image","ResourceKind":"LocalFile","RootPath":"https://docserverpaaprodeus.blob.core.windows.net/3e26f85d-8adb-4d2e-9036-b96b51946287-1/resource/1.png?sv=2017-04-17&sr=b&sig=fkRsBslUCwdYdNGgqAf1MtgA5Idwm9GZ0uQDIyGjRa4%3D&spr=https&se=2020-07-08T15%3A06%3A27Z&sp=r"},{"Name":"1048232144.jpg.0","Schema":"i","IsSampleData":false,"IsWritable":false,"Type":"ResourceInfo","FileName":"0002.jpg","Path":"Assets\\Images\\0002.jpg","Content":"Image","ResourceKind":"LocalFile","RootPath":"https://docserverpaaprodeus.blob.core.windows.net/3e26f85d-8adb-4d2e-9036-b96b51946287-1/resource/2.jpg?sv=2017-04-17&sr=b&sig=cXhlS2Eg%2FtOhD5N%2F14Y36bwm%2FOYMJzXEfUxeq%2FGnr2c%3D&spr=https&se=2020-07-08T15%3A07%3A31Z&sp=r"}]}